amoreqq/__init__.py
amoreqq/main.py
amoreqq/utils.py
amoreqq/version.py
amoreqq/models/__init__.py
amoreqq/models/amoreqq_api.py
amoreqq/models/exceptions/__init__.py
amoreqq/models/exceptions/amoreqq_api.py
amoreqq/models/exceptions/base.py
amoreqq-7.7.7.dist-info/METADATA
amoreqq-7.7.7.dist-info/WHEEL
amoreqq-7.7.7.dist-info/top_level.txt
amoreqq-7.7.7.dist-info/RECORD
