Metadata-Version: 2.1
Name: amoreqq
Version: 7.7.7
Home-page: https://github.com/AmoreForever/amore-qq
Download-URL: https://github.com/AmoreForever/amore-qq/archive/main.zip
Author: Amore
Author-email: me.thefarkhodov@gmail.com
License: MIT
Keywords: qq,different dimension me,anime,ai
Classifier: Programming Language :: Python :: 3.10
Requires-Dist: httpx (~=0.23.1)
Requires-Dist: pydantic (~=1.10.2)
